dcsv.py
dcsv-1.1.1.dist-info/licenses/LICENSE
dcsv-1.1.1.dist-info/METADATA
dcsv-1.1.1.dist-info/WHEEL
dcsv-1.1.1.dist-info/top_level.txt
dcsv-1.1.1.dist-info/RECORD
